CHANGES.txt
MANIFEST
MANIFEST.in
README.txt
setup.py
ZenPacks/__init__.py
ZenPacks.lbn.LDAPMonitor.egg-info/PKG-INFO
ZenPacks.lbn.LDAPMonitor.egg-info/SOURCES.txt
ZenPacks.lbn.LDAPMonitor.egg-info/dependency_links.txt
ZenPacks.lbn.LDAPMonitor.egg-info/entry_points.txt
ZenPacks.lbn.LDAPMonitor.egg-info/namespace_packages.txt
ZenPacks.lbn.LDAPMonitor.egg-info/not-zip-safe
ZenPacks.lbn.LDAPMonitor.egg-info/requires.txt
ZenPacks.lbn.LDAPMonitor.egg-info/top_level.txt
ZenPacks/lbn/__init__.py
ZenPacks/lbn/LDAPMonitor/__init__.py
ZenPacks/lbn/LDAPMonitor/config.py
ZenPacks/lbn/LDAPMonitor/configure.zcml
ZenPacks/lbn/LDAPMonitor/info.py
ZenPacks/lbn/LDAPMonitor/interfaces.py
ZenPacks/lbn/LDAPMonitor/monparsers.py
ZenPacks/lbn/LDAPMonitor/setuphandlers.py
ZenPacks/lbn/LDAPMonitor/zenperfldap.py
ZenPacks/lbn/LDAPMonitor/daemons/zenperfldap
ZenPacks/lbn/LDAPMonitor/datasources/LDAPDataSource.py
ZenPacks/lbn/LDAPMonitor/datasources/__init__.py
ZenPacks/lbn/LDAPMonitor/services/LDAPConfigService.py
ZenPacks/lbn/LDAPMonitor/services/__init__.py
ZenPacks/lbn/LDAPMonitor/tests/__init__.py